minecraftserverapi/__init__.py
minecraftserverapi/core.py
minecraftserverapi-2.0.2.dist-info/licenses/LICENSE
minecraftserverapi-2.0.2.dist-info/METADATA
minecraftserverapi-2.0.2.dist-info/WHEEL
minecraftserverapi-2.0.2.dist-info/entry_points.txt
minecraftserverapi-2.0.2.dist-info/top_level.txt
minecraftserverapi-2.0.2.dist-info/RECORD
