Metadata-Version: 2.4
Name: minecraftserverapi
Version: 2.0.2
Summary: Librería para crear y gestionar servidores Minecraft Paper, Forge y Fabric con ngrok.
Home-page: https://github.com/notV4FAB/minecraftserverapi
Author: Bautista Fabris
Author-email: tu.email@ejemplo.com
Classifier: Programming Language :: Python :: 3
Classifier: Operating System :: OS Independent
Classifier: License :: OSI Approved :: MIT License
Requires-Python: >=3.7
License-File: LICENSE
Requires-Dist: requests>=2.25.0
Requires-Dist: utilfab>=1.1.0
Dynamic: author
Dynamic: author-email
Dynamic: classifier
Dynamic: description
Dynamic: description-content-type
Dynamic: home-page
Dynamic: license-file
Dynamic: requires-dist
Dynamic: requires-python
Dynamic: summary
